nbspellcheck/__init__.py
nbspellcheck/nbspellcheck.py
nbspellcheck-0.0.4.data/scripts/nbspellcheck.py
nbspellcheck-0.0.4.dist-info/LICENSE
nbspellcheck-0.0.4.dist-info/METADATA
nbspellcheck-0.0.4.dist-info/WHEEL
nbspellcheck-0.0.4.dist-info/top_level.txt
nbspellcheck-0.0.4.dist-info/RECORD
