Metadata-Version: 2.1
Name: nbspellcheck
Version: 0.0.4
Summary: Spell checker for jupyter notebooks
Home-page: https://github.com/cbernet/nbspellcheck
Author: Colin Bernet
Author-email: colin.bernet@gmail.com
License: UNKNOWN
Platform: UNKNOWN
Classifier: Programming Language :: Python :: 3
Classifier: License :: OSI Approved :: MIT License
Classifier: Operating System :: OS Independent
Requires-Python: >3.5
Requires-Dist: pyspellchecker
Requires-Dist: termcolor
Requires-Dist: nltk
